lsm_params_env/__init__.py
lsm_params_env/envs/__init__.py
lsm_params_env/envs/env_lsm.py
lsm_params_env-0.0.3.dist-info/METADATA
lsm_params_env-0.0.3.dist-info/WHEEL
lsm_params_env-0.0.3.dist-info/top_level.txt
lsm_params_env-0.0.3.dist-info/RECORD
