Metadata-Version: 2.1
Name: lsm-params-env
Version: 0.0.3
Summary: A openAI Gym Env for lsm
Home-page: UNKNOWN
License: UNKNOWN
Platform: UNKNOWN
Requires-Dist: gym
